log_count_util/__init__.py
log_count_util/_core.cp39-win32.pyd
log_count_util/_core.pyi
log_count_util/wrapper.py
log_count_util-0.1.0.dist-info/METADATA
log_count_util-0.1.0.dist-info/WHEEL
log_count_util-0.1.0.dist-info/top_level.txt
log_count_util-0.1.0.dist-info/RECORD
