Metadata-Version: 2.1
Name: log-count-util
Version: 0.1.0
Summary: A utility module to count/aggregate logs along time.
Home-page: UNKNOWN
Author: Tomoki Ohtsuki
Author-email: tomoki.otsuki129@gmail.com
License: UNKNOWN
Platform: UNKNOWN
Requires-Python: >=3.6
Requires-Dist: numpy (>=1.11)
